functions/__init__.py
functions/aws_helper.py
functions/date_helper.py
functions/delta_helpers.py
functions/drive_helper.py
functions/email_helper.py
functions/emails_helper.py
functions/emr_helper.py
functions/glue_helper.py
functions/prueba_helper.py
functions/slack_helper.py
functions/spark_helper.py
functions/tableau_helper.py
data_morbius_pomelo-0.1.1.dist-info/METADATA
data_morbius_pomelo-0.1.1.dist-info/WHEEL
data_morbius_pomelo-0.1.1.dist-info/top_level.txt
data_morbius_pomelo-0.1.1.dist-info/RECORD
