Metadata-Version: 2.1
Name: data-morbius-pomelo
Version: 0.1.1
Summary: Funciones cross data
Home-page: https://github.com/pomelo-la/infra-data-utilities
Author: bruno
Author-email: bruno.iungano@pomelo.la
License: MIT
Classifier: Programming Language :: Python :: 3
Classifier: License :: OSI Approved :: MIT License
Classifier: Operating System :: OS Independent
Requires-Python: >=3.6
Requires-Dist: requests
Requires-Dist: numpy
